rag_oracle-0.1.0.dist-info/licenses/LICENSE
rag_pipeline/__init__.py
rag_pipeline/analytics_engine.py
rag_pipeline/answer_intent_classifier.py
rag_pipeline/chunker.py
rag_pipeline/concept_type_separator.py
rag_pipeline/config.py
rag_pipeline/conflict_resolver.py
rag_pipeline/cost_optimizer.py
rag_pipeline/counterfactual_fix_generator.py
rag_pipeline/document_loader.py
rag_pipeline/embeddings.py
rag_pipeline/evaluator.py
rag_pipeline/exact_failure_point.py
rag_pipeline/failure_attribution.py
rag_pipeline/failure_detector.py
rag_pipeline/failure_surface_mapper.py
rag_pipeline/fix_impact_estimator.py
rag_pipeline/generator.py
rag_pipeline/phase8_recommender.py
rag_pipeline/pipeline.py
rag_pipeline/query_feasibility_analyzer.py
rag_pipeline/rag_oracle.py
rag_pipeline/retriever.py
rag_pipeline/root_cause_oracle.py
rag_pipeline/self_healer.py
rag_pipeline/tracer.py
rag_oracle-0.1.0.dist-info/METADATA
rag_oracle-0.1.0.dist-info/WHEEL
rag_oracle-0.1.0.dist-info/top_level.txt
rag_oracle-0.1.0.dist-info/RECORD
