Metadata-Version: 2.4
Name: rag-oracle
Version: 0.1.0
Summary: RAG Oracle – failure diagnostics for Retrieval-Augmented Generation systems
Author: MUHAMMAD HASSAN SHAHBAZ
License: MIT
Project-URL: Homepage, https://github.com/Rana-Hassan7272/RAG-ORACLE
Project-URL: Documentation, https://github.com/Rana-Hassan7272/RAG-ORACLE#readme
Project-URL: Repository, https://github.com/Rana-Hassan7272/RAG-ORACLE
Project-URL: Issues, https://github.com/Rana-Hassan7272/RAG-ORACLE/issues
Keywords: rag,llm,retrieval-augmented-generation,failure-detection,diagnostics,root-cause-analysis
Classifier: Development Status :: 3 - Alpha
Classifier: Intended Audience :: Developers
Classifier: License :: OSI Approved :: MIT License
Classifier: Programming Language :: Python :: 3
Classifier: Programming Language :: Python :: 3.8
Classifier: Programming Language :: Python :: 3.9
Classifier: Programming Language :: Python :: 3.10
Classifier: Programming Language :: Python :: 3.11
Classifier: Topic :: Software Development :: Libraries :: Python Modules
Classifier: Topic :: Scientific/Engineering :: Artificial Intelligence
Requires-Python: >=3.8
License-File: LICENSE
Requires-Dist: langchain>=0.1.0
Requires-Dist: langchain-core>=0.1.0
Requires-Dist: langchain-community>=0.0.20
Requires-Dist: langchain-openai>=0.0.5
Requires-Dist: langchain-text-splitters>=0.0.1
Requires-Dist: langchain-groq>=0.0.1
Requires-Dist: pypdf>=3.17.0
Requires-Dist: chromadb>=0.4.22
Requires-Dist: langchain-huggingface>=0.0.1
Requires-Dist: sentence-transformers>=2.2.2
Requires-Dist: python-dotenv>=1.0.0
Requires-Dist: scikit-learn>=1.3.0
Requires-Dist: numpy>=1.24.0
Provides-Extra: dev
Requires-Dist: pytest>=7.0.0; extra == "dev"
Requires-Dist: pytest-cov>=4.0.0; extra == "dev"
Requires-Dist: black>=23.0.0; extra == "dev"
Requires-Dist: flake8>=6.0.0; extra == "dev"
Dynamic: license-file
